MANIFEST.in
README.txt
setup.cfg
setup.py
docs/HISTORY.txt
docs/INSTALL.txt
docs/LICENSE.GPL
docs/LICENSE.txt
quintagroup/__init__.py
quintagroup.pfg.captcha.egg-info/PKG-INFO
quintagroup.pfg.captcha.egg-info/SOURCES.txt
quintagroup.pfg.captcha.egg-info/dependency_links.txt
quintagroup.pfg.captcha.egg-info/entry_points.txt
quintagroup.pfg.captcha.egg-info/namespace_packages.txt
quintagroup.pfg.captcha.egg-info/not-zip-safe
quintagroup.pfg.captcha.egg-info/requires.txt
quintagroup.pfg.captcha.egg-info/top_level.txt
quintagroup/pfg/__init__.py
quintagroup/pfg/captcha/README.txt
quintagroup/pfg/captcha/__init__.py
quintagroup/pfg/captcha/config.py
quintagroup/pfg/captcha/configure.zcml
quintagroup/pfg/captcha/field.py
quintagroup/pfg/captcha/setuphandlers.py
quintagroup/pfg/captcha/validator.py
quintagroup/pfg/captcha/version.txt
quintagroup/pfg/captcha/widget.py
quintagroup/pfg/captcha/profiles/default/factorytool.xml
quintagroup/pfg/captcha/profiles/default/import_steps.xml
quintagroup/pfg/captcha/profiles/default/metadata.xml
quintagroup/pfg/captcha/profiles/default/propertiestool.xml
quintagroup/pfg/captcha/profiles/default/quintagroup.pfg.captcha_default.txt
quintagroup/pfg/captcha/profiles/default/quintagroup_pfg_captcha.txt
quintagroup/pfg/captcha/profiles/default/skins.xml
quintagroup/pfg/captcha/profiles/default/types.xml
quintagroup/pfg/captcha/profiles/default/workflows.xml
quintagroup/pfg/captcha/profiles/default/types/CaptchaField.xml
quintagroup/pfg/captcha/profiles/default/types/FormFolder.xml
quintagroup/pfg/captcha/skins/qplonecaptchafield/captchaField_widget.pt
quintagroup/pfg/captcha/skins/qplonecaptchafield/captcha_field.gif
quintagroup/pfg/captcha/tests/__init__.py
quintagroup/pfg/captcha/tests/base.py
quintagroup/pfg/captcha/tests/testInstalled.py
quintagroup/pfg/captcha/tests/testMigration.py