Metadata-Version: 1.0
Name: quintagroup.pfg.captcha
Version: 1.0.5
Summary: quintagroup.pfg.captcha is a package that allows to add captcha field to PloneFormGen forms.
Home-page: http://projects.quintagroup.com/products/wiki/quintagroup.pfg.captcha
Author: Quintagroup
Author-email: support@quintagroup.com
License: GPL
Keywords: plone captcha PloneFormGen
Platform: UNKNOWN
Classifier: Framework :: Plone
Classifier: Programming Language :: Python
Classifier: Topic :: Software Development :: Libraries :: Python Modules
